Metadata-Version: 2.1
Name: plottify
Version: 1.1
Summary: Plottify
Home-page: https://github.com/andrewcharlesjones/plottify
Author: Andy Jones
Author-email: ajones788@gmail.com
License: MIT
Download-URL: https://github.com/andrewcharlesjones/plottify/archive/refs/tags/v1.1.tar.gz
Platform: UNKNOWN
Classifier: License :: OSI Approved :: MIT License
Classifier: Framework :: Matplotlib
Classifier: Programming Language :: Python :: 3
Classifier: Programming Language :: Python :: 3 :: Only
Classifier: Programming Language :: Python :: 3.6
Classifier: Programming Language :: Python :: 3.7
Classifier: Programming Language :: Python :: 3.8
Classifier: Programming Language :: Python :: 3.9
Classifier: Programming Language :: Python :: 3.10
Requires-Python: >=3.6
License-File: LICENSE.txt
